napari_layer_divider/__init__.py
napari_layer_divider/_version.py
napari_layer_divider/_widget.py
napari_layer_divider/napari.yaml
napari_layer_divider/_tests/__init__.py
napari_layer_divider/_tests/test_widget.py
napari_layer_divider-0.0.3.dist-info/licenses/LICENSE
napari_layer_divider-0.0.3.dist-info/METADATA
napari_layer_divider-0.0.3.dist-info/WHEEL
napari_layer_divider-0.0.3.dist-info/entry_points.txt
napari_layer_divider-0.0.3.dist-info/top_level.txt
napari_layer_divider-0.0.3.dist-info/RECORD
